fstui/__init__.py
fstui/autoform.py
fstui/form_generator.py
fstui/packager.py
fstui-0.1.1.dist-info/METADATA
fstui-0.1.1.dist-info/WHEEL
fstui-0.1.1.dist-info/licenses/LICENSE
fstui-0.1.1.dist-info/RECORD
