Metadata-Version: 2.4
Name: fstui
Version: 0.1.1
Summary: Terminal UI toolkit for file packaging and Pydantic form generation. Includes dual-panel file organizer, archive creation, and auto-generated forms for Pydantic models using Textual.
Author-email: HYChou0515 <hychou.svm@example.com>
License: MIT License
License-File: LICENSE
Keywords: archive,file-manager,form,pydantic,rich,tar,terminal-ui,textual,tui,typer,zip
Classifier: Development Status :: 4 - Beta
Classifier: Environment :: Console
Classifier: Framework :: Pydantic :: 2
Classifier: Intended Audience :: Developers
Classifier: License :: OSI Approved :: MIT License
Classifier: Operating System :: OS Independent
Classifier: Programming Language :: Python :: 3
Classifier: Programming Language :: Python :: 3.11
Classifier: Programming Language :: Python :: 3.12
Classifier: Programming Language :: Python :: 3.13
Classifier: Topic :: Software Development :: User Interfaces
Classifier: Topic :: Utilities
Requires-Python: >=3.11
Requires-Dist: pydantic>=2.11.7
Requires-Dist: rich>=14.2.0
Requires-Dist: textual>=6.6.0
Requires-Dist: typer>=0.20.0
